scrapy_colorlog-0.1.1.dist-info/METADATA
scrapy_colorlog-0.1.1.dist-info/WHEEL
scrapy_colorlog/__init__.py
scrapy_colorlog/formatter.py
scrapy_colorlog/py.typed
scrapy_colorlog/utils.py
scrapy_colorlog-0.1.1.dist-info/RECORD
