Metadata-Version: 2.1
Name: scrapy-colorlog
Version: 0.1.1
Summary: Color log output support for Scrapy
Author: divtiply
License: MIT
Classifier: Intended Audience :: Developers
Classifier: Operating System :: OS Independent
Classifier: Framework :: Scrapy
Classifier: Programming Language :: Python :: 3
Classifier: Typing :: Typed
Project-URL: Repository, https://github.com/divtiply/scrapy-colorlog
Requires-Python: >=3.7
Requires-Dist: scrapy>=1.0.0
Requires-Dist: colorlog>=6.6.0
Requires-Dist: typing-extensions>=4.0.0
